{"metadata": {"source": "Baum et al, Trends in Student Aid 2016, The College Board", "notes": null}, "series": "Loan amount", "axis": {"rotated": false, "x": {"type": "category", "categories": ["2000-01", "2005-6", "2010-11", "2015-16"]}, "y": {"tick": {"format": "dollar"}}}, "data": {"labels": {"format": "dollar"}, "columns": [["Loan amount", 10600, 13200, 14000, 15300]], "type": "bar"}, "title": "Average Annual Parent PLUS Loan per Borrower and Percentage of Dependent Students’ Parents Borrowing, 2000-01 to 2015-16"}