{"axis": {"rotated": true, "y": {"tick": {"format": "percent"}}, "x": {"type": "category", "categories": ["All undergraduates", "First-year undergraduates"]}}, "title": "Distribution of Family Income Among All Dependent Undergraduates versus First-Year Only", "series": ["Less than $30,000", "$30,000–64,999", "$65,000–105,999", "$106,000 or more"], "metadata": {"source": "National Postsecondary Student Aid Study 2012", "notes": null}, "data": {"type": "bar", "groups": [["Less than $30,000", "$30,000–64,999", "$65,000–105,999", "$106,000 or more"]], "labels": {"format": "percent"}, "columns": [["Less than $30,000", 0.2529, 0.3196], ["$30,000–64,999", 0.2427, 0.2533], ["$65,000–105,999", 0.2529, 0.226], ["$106,000 or more", 0.2515, 0.2011]]}}